pyfrigel_report_tool/__init__.py
pyfrigel_report_tool/consts.py
pyfrigel_report_tool/frigel_report_creator.py
pyfrigel_report_tool/syncro_report_creator.py
pyfrigel_report_tool/translations.py
pyfrigel_report_tool/assets/.DS_Store
pyfrigel_report_tool/assets/Calibri-Bold.ttf
pyfrigel_report_tool/assets/Calibri.ttf
pyfrigel_report_tool/assets/RSY_con_display.jpeg
pyfrigel_report_tool/assets/Syncro.png
pyfrigel_report_tool/assets/frigel_logo.png
pyfrigel_report_tool/assets/Ubuntu/.DS_Store
pyfrigel_report_tool/assets/Ubuntu/Ubuntu-Bold.ttf
pyfrigel_report_tool/assets/Ubuntu/Ubuntu-BoldItalic.ttf
pyfrigel_report_tool/assets/Ubuntu/Ubuntu-Italic.ttf
pyfrigel_report_tool/assets/Ubuntu/Ubuntu-Light.ttf
pyfrigel_report_tool/assets/Ubuntu/Ubuntu-LightItalic.ttf
pyfrigel_report_tool/assets/Ubuntu/Ubuntu-Medium.ttf
pyfrigel_report_tool/assets/Ubuntu/Ubuntu-MediumItalic.ttf
pyfrigel_report_tool/assets/Ubuntu/Ubuntu-Regular.ttf
pyfrigel_report_tool/charts/__init__.py
pyfrigel_report_tool/charts/charts.py
pyfrigel_report_tool-1.5.dist-info/LICENSE.txt
pyfrigel_report_tool-1.5.dist-info/METADATA
pyfrigel_report_tool-1.5.dist-info/WHEEL
pyfrigel_report_tool-1.5.dist-info/top_level.txt
pyfrigel_report_tool-1.5.dist-info/RECORD
