Metadata-Version: 2.1
Name: pyfrigel-report-tool
Version: 1.5
Summary: Package for the creation of Frigel reports
Home-page: http://pypi.python.org/pypi/pyfrigel-report-tool/
License: LICENSE.txt
License-File: LICENSE.txt
Requires-Dist: reportlab
Requires-Dist: numpy
